python_yate-0.5.0.dist-info/licenses/LICENSE
yate/__init__.py
yate/asyncio.py
yate/callgen.py
yate/ivr.py
yate/protocol.py
yate/yate.py
python_yate-0.5.0.dist-info/METADATA
python_yate-0.5.0.dist-info/WHEEL
python_yate-0.5.0.dist-info/entry_points.txt
python_yate-0.5.0.dist-info/top_level.txt
python_yate-0.5.0.dist-info/RECORD
