Metadata-Version: 2.4
Name: python-yate
Version: 0.5.0
Summary: An (asyncio enabled) python library for yate IVRs and extmodules
Home-page: https://github.com/eventphone/python-yate
Author: Martin Lang
Author-email: Martin.Lang@rwth-aachen.de
License: MIT
Classifier: Programming Language :: Python :: 3
Classifier: Programming Language :: Python :: 3.11
Classifier: Programming Language :: Python :: 3.12
Classifier: Programming Language :: Python :: 3.13
Classifier: License :: OSI Approved :: MIT License
License-File: LICENSE
Dynamic: author
Dynamic: author-email
Dynamic: classifier
Dynamic: description
Dynamic: description-content-type
Dynamic: home-page
Dynamic: license
Dynamic: license-file
Dynamic: summary
